citation_title/__init__.py
citation_title/adverse.py
citation_title/inre.py
citation_title/titles.py
citation_title/litigants/__init__.py
citation_title/litigants/humans.py
citation_title/litigants/offices.py
citation_title/litigants/utils.py
citation_title-0.0.2.dist-info/METADATA
citation_title-0.0.2.dist-info/WHEEL
citation_title-0.0.2.dist-info/top_level.txt
citation_title-0.0.2.dist-info/RECORD
