Metadata-Version: 2.4
Name: citation-title
Version: 0.0.2
Summary: Pattern matching Philippine Supreme Court citations.
Requires-Python: >=3.13
